{"errors":[],"warnings":[],"namedChunkGroups":{"app":{"chunks":[6,5,2],"assets":["webpack-runtime-f4076c3aabd37fb9760a.js","webpack-runtime-f4076c3aabd37fb9760a.js.map","framework-d9cf0f47b747b267fae2.js","framework-d9cf0f47b747b267fae2.js.map","app-d46dbad6205c1c027bf3.js","app-d46dbad6205c1c027bf3.js.map"],"children":{},"childAssets":{}},"component---src-pages-404-js":{"chunks":[1,0,3],"assets":["styles.d91bf5cf3cdddd9aa350.css","styles-c2fe8482057191dca484.js","styles-c2fe8482057191dca484.js.map","commons-1e1ae53c4d0d235fb294.js","commons-1e1ae53c4d0d235fb294.js.map","component---src-pages-404-js-b8f651dc4905d46775b6.js","component---src-pages-404-js-b8f651dc4905d46775b6.js.map"],"children":{},"childAssets":{}},"component---src-pages-index-js":{"chunks":[1,0,4],"assets":["styles.d91bf5cf3cdddd9aa350.css","styles-c2fe8482057191dca484.js","styles-c2fe8482057191dca484.js.map","commons-1e1ae53c4d0d235fb294.js","commons-1e1ae53c4d0d235fb294.js.map","component---src-pages-index-js-9d1589552c958931ec9d.js","component---src-pages-index-js-9d1589552c958931ec9d.js.map"],"children":{},"childAssets":{}}},"assetsByChunkName":{"app":["webpack-runtime-f4076c3aabd37fb9760a.js","framework-d9cf0f47b747b267fae2.js","app-d46dbad6205c1c027bf3.js"],"component---src-pages-404-js":["styles.d91bf5cf3cdddd9aa350.css","styles-c2fe8482057191dca484.js","commons-1e1ae53c4d0d235fb294.js","component---src-pages-404-js-b8f651dc4905d46775b6.js"],"component---src-pages-index-js":["styles.d91bf5cf3cdddd9aa350.css","styles-c2fe8482057191dca484.js","commons-1e1ae53c4d0d235fb294.js","component---src-pages-index-js-9d1589552c958931ec9d.js"]}}